LICENSE.txt
MANIFEST.in
README.rst
setup.cfg
setup.py
pyredis/__init__.py
pyredis/client.py
pyredis/commands.py
pyredis/connection.py
pyredis/exceptions.py
pyredis/helper.py
pyredis/pool.py
pyredis/protocol.py
python_redis.egg-info/PKG-INFO
python_redis.egg-info/SOURCES.txt
python_redis.egg-info/dependency_links.txt
python_redis.egg-info/top_level.txt