Metadata-Version: 1.1
Name: python-redis
Version: 0.0.1
Summary: Implementation of PEP 3143, a unix daemon
Home-page: https://github.com/schlitzered/pyredis
Author: schlitzer
Author-email: stephan.schultchen@gmail.com
License: MIT
Keywords: redis
Platform: posix
Classifier: License :: OSI Approved :: MIT License
Classifier: Programming Language :: Python :: 3
